civilservant/env/__version__.py
civilservant/env/cli.py
civilservant/env/namespace.py
civilservant/env/pipenv.py
civilservant/env/tasks/db.py
civilservant/env/tasks/dist.py
civilservant/env/tasks/env.py
civilservant/env/utils/dotenv.py
civilservant/env/utils/env_template.py
civilservant/env/utils/package.py
civilservant/env/utils/print.py
civilservant-0.0.8.dist-info/LICENSE
civilservant-0.0.8.dist-info/METADATA
civilservant-0.0.8.dist-info/WHEEL
civilservant-0.0.8.dist-info/entry_points.txt
civilservant-0.0.8.dist-info/top_level.txt
civilservant-0.0.8.dist-info/RECORD
