Metadata-Version: 2.1
Name: civilservant
Version: 0.0.8
Summary: The environment manager for CivilServant's experimentation platform
Home-page: UNKNOWN
Author: The CivilServant Team
Author-email: "system.operations@civilservant.io"
License: MIT
Platform: UNKNOWN
Classifier: License :: OSI Approved :: MIT License
Classifier: Intended Audience :: Science/Research
Classifier: Intended Audience :: Developers
Classifier: Programming Language :: Python
Classifier: Programming Language :: Python :: 3
Classifier: Programming Language :: Python :: 3.7
Classifier: Programming Language :: Python :: Implementation :: CPython
Classifier: Topic :: Software Development
Classifier: Topic :: Scientific/Engineering
Requires-Python: >= 3.7
Requires-Dist: alembic
Requires-Dist: invoke
Requires-Dist: python-dotenv
Requires-Dist: pytest
Requires-Dist: toml
Requires-Dist: twine
